aprende_oper4nd0-0.1.0.dist-info/licenses/LICENSE
aprendeoper4nd0/__init__.py
aprendeoper4nd0/codigo.py
aprende_oper4nd0-0.1.0.dist-info/METADATA
aprende_oper4nd0-0.1.0.dist-info/WHEEL
aprende_oper4nd0-0.1.0.dist-info/top_level.txt
aprende_oper4nd0-0.1.0.dist-info/RECORD
