Metadata-Version: 2.4
Name: aprende-oper4nd0
Version: 0.1.0
Summary: Librería con funciones básicas de operaciones con número
Author: Marcos Almorox
Requires-Python: >=3.8
License-File: LICENSE
Dynamic: license-file
